user_voting_rocks/__init__.py
user_voting_rocks/cli.py
user_voting_rocks/model.py
user_voting_rocks/parse.py
user_voting_rocks/stop_words.py
user_voting_rocks-0.3.2.dist-info/AUTHORS.rst
user_voting_rocks-0.3.2.dist-info/LICENSE
user_voting_rocks-0.3.2.dist-info/METADATA
user_voting_rocks-0.3.2.dist-info/WHEEL
user_voting_rocks-0.3.2.dist-info/entry_points.txt
user_voting_rocks-0.3.2.dist-info/top_level.txt
user_voting_rocks-0.3.2.dist-info/RECORD
