Metadata-Version: 2.1
Name: user-voting-rocks
Version: 0.3.2
Summary: Use your personal talk voting for PyConDE 2019 to predict your interest in a talk.
Home-page: https://github.com/luphord/user_voting_rocks
Author: luphord
Author-email: luphord@protonmail.com
License: MIT license
Keywords: user_voting_rocks
Platform: UNKNOWN
Classifier: Development Status :: 2 - Pre-Alpha
Classifier: Intended Audience :: Developers
Classifier: License :: OSI Approved :: MIT License
Classifier: Natural Language :: English
Classifier: Programming Language :: Python :: 3
Classifier: Programming Language :: Python :: 3.7
Requires-Dist: Click (>=6.0)
Requires-Dist: beautifulsoup4 (>=4.7jupyter>=1.0)
Requires-Dist: scikit-learn (>=0.20)
Requires-Dist: joblib (>=0.13)
